<?xml version="1.0" ?>
<ISSUE>
  <ISSUENO>24877</ISSUENO>
  <ISSUEURL>https://github.com/Dolibarr/dolibarr/issues/24877</ISSUEURL>
  <TITLE>DB_ERROR_NOSUCHFIELD 'status' in 'where clause'</TITLE>
  <DESCRIPTION>### Bug Hello, I have an issu that I can't fix. Is anybody can help ? Thanks in advance. Dolibarr a détecté une erreur technique. Ces informations peuvent être utiles à des fins de diagnostic (vous pouvez définir l'option $dolibarr_main_prod sur '1' pour masquer les informations sensibles): Date: 20230525124329 Dolibarr: 17.0.1 - https://www.dolibarr.org Niveau de fonctionnalités: 0 PHP: 7.4.33 Server: Apache OS: Linux webd003.cluster021.gra.hosting.ovh.net 5.15.80-ovh-vps-grsec-zfs-classid #1 SMP Wed Nov 30 08:49:06 UTC 2022 x86_64 User Agent: Mozilla/5.0 (Macintosh; Intel Mac OS X 10_15_7) AppleWebKit/605.1.15 (KHTML, like Gecko) Version/16.5 Safari/605.1.15 Url sollicitée: /htdocs/product/stock/list.php?leftmenu= Gestionnaire de menu: eldy_menu.php Modules/Applications: user, syslog, supplier_proposal, agenda, barcode, fckeditor, cron, commande, ecm, facture, fournisseur, margin, printing, service, societe, categorie, projet, bom, propal, mrp, debugbar, bookmark, expedition, incoterm, workflow, product, stock, reception, productbatch, notification Type gestionnaire de base de données: mysqli Requête dernier accès en base en erreur: SELECT t.rowid, t.ref,t.lieu FROM llx_entrepot as t WHERE 1=1 AND t.entity IN (1) AND ((status = 1 AND entity IN (1))) ORDER BY t.ref ASC, t.lieu ASC Code retour dernier accès en base en erreur: DB_ERROR_NOSUCHFIELD Information sur le dernier accès en base en erreur: Unknown column 'status' in 'where clause' ### Environment Version _No response_ ### Environment OS _No response_ ### Environment Web server _No response_ ### Environment PHP _No response_ ### Environment Database _No response_ ### Environment URL(s) _No response_ ### Expected and actual behavior _No response_ ### Steps to reproduce the behavior _No response_ ### Attached files _No response_</DESCRIPTION>
  <REPONAME>dolibarr</REPONAME>
  <TIMEDIFFERENCEDAYS>15</TIMEDIFFERENCEDAYS>
  <BUGGYCOMMIT>
    <MESSAGE>Fix phpcs</MESSAGE>
    <SHA>d853a8f2207acacbc1de0c7c7690533dc7344969</SHA>
  </BUGGYCOMMIT>
  <PATCHCOMMITS>
    <COMMIT>
      <MESSAGE>fix for #24877</MESSAGE>
      <SHA>2616b97d1737f2e36044a13b4a1569729c1cb4ac</SHA>
      <PATCHEDFILES>
        <FILE>htdocs/product/stock/class/entrepot.class.php</FILE>
      </PATCHEDFILES>
    </COMMIT>
    <COMMIT>
      <MESSAGE>Merge pull request #25000 from yledoare/17.0 fix for #24877</MESSAGE>
      <SHA>6eb117517acb8fd22f5c4ded39235d992ba45959</SHA>
      <PATCHEDFILES>
        <FILE>htdocs/product/stock/class/entrepot.class.php</FILE>
      </PATCHEDFILES>
    </COMMIT>
  </PATCHCOMMITS>
</ISSUE>
