<?xml version="1.0" ?>
<ISSUE>
  <ISSUENO>7637</ISSUENO>
  <ISSUEURL>https://github.com/nopSolutions/nopCommerce/issues/7637</ISSUEURL>
  <TITLE>Javascript error caused by missing braces</TITLE>
  <DESCRIPTION>https://github.com/nopSolutions/nopCommerce/blob/d811838f678527c203b49ae8e656d390ba00656f/src/Presentation/Nop.Web/Views/Shared/Components/TopMenu/Default.cshtml#L159 Please note that closing braces are missing.</DESCRIPTION>
  <REPONAME>nopCommerce</REPONAME>
  <TIMEDIFFERENCEDAYS>0</TIMEDIFFERENCEDAYS>
  <BUGGYCOMMIT>
    <MESSAGE>#7618 Display custom address attributes for the billing address in the order details page</MESSAGE>
    <SHA>5f11de2a4e83454e1380198e3edc880fd5a45db3</SHA>
  </BUGGYCOMMIT>
  <PATCHCOMMITS>
    <COMMIT>
      <MESSAGE>#7637 Javascript error caused by missing braces</MESSAGE>
      <SHA>c0c3da066dcb91631c4abdd861e4ac17ddf42bc2</SHA>
      <PATCHEDFILES>
        <FILE>src/Presentation/Nop.Web/Views/Shared/Components/TopMenu/Default.cshtml</FILE>
      </PATCHEDFILES>
    </COMMIT>
  </PATCHCOMMITS>
</ISSUE>
