<?xml version="1.0" ?>
<ISSUE>
  <ISSUENO>6476</ISSUENO>
  <ISSUEURL>https://github.com/nopSolutions/nopCommerce/issues/6476</ISSUEURL>
  <TITLE>Match URL path and breadcrumbs on a product page when &quot;Product URL structure type&quot; is Category</TITLE>
  <DESCRIPTION>nopCommerce version: 4.60 Steps to reproduce the problem: Step 1: Redirect on Admin panel &gt; Configuration &gt; Settings &gt; Catalog setting &gt; Product page tab &gt; Product URL structure type as (/category/product) Step 2: Create 1 product from admin side Step 3: Add multiple category from this product from admin side. Step 4: Save product and redirect on public side Step 5: Open Configured product from any category Step 6: Observe that Slug and Breadcrumb is not showing proper Expected result: Slug and Breadcrumb should show proper Please refer attachment ![Slug_breadcrumb ](https://user-images.githubusercontent.com/82799708/208871616-33235f3f-bdf9-4500-8485-d2de8035a472.png)</DESCRIPTION>
  <REPONAME>nopCommerce</REPONAME>
  <TIMEDIFFERENCEDAYS>19</TIMEDIFFERENCEDAYS>
  <BUGGYCOMMIT>
    <MESSAGE>#6494 Fixed problem with edit button during selecting the shipping address</MESSAGE>
    <SHA>a8abdd94355136f3011deb695854da0452bad855</SHA>
  </BUGGYCOMMIT>
  <PATCHCOMMITS>
    <COMMIT>
      <MESSAGE>#6476 Match URL path and breadcrumbs on a product page</MESSAGE>
      <SHA>0d6fc502d8455ad8123135ff768f98c3b71e08e3</SHA>
      <PATCHEDFILES>
        <FILE>src/Presentation/Nop.Web.Framework/Mvc/Routing/NopUrlHelper.cs</FILE>
        <FILE>src/Presentation/Nop.Web.Framework/Mvc/Routing/SlugRouteTransformer.cs</FILE>
      </PATCHEDFILES>
    </COMMIT>
  </PATCHCOMMITS>
</ISSUE>
