<?xml version="1.0" ?>
<ISSUE>
  <ISSUENO>2189</ISSUENO>
  <ISSUEURL>https://github.com/nopSolutions/nopCommerce/issues/2189</ISSUEURL>
  <TITLE>Page not found. HTML source code shown due to missing Content Type</TITLE>
  <DESCRIPTION>Source: http://www.nopcommerce.com/boards/t/46447/commoncontroller-pagenotfound-html-source-code-shown-due-to-missing-content-type.aspx But we can be reproduced it locally only</DESCRIPTION>
  <REPONAME>nopCommerce</REPONAME>
  <TIMEDIFFERENCEDAYS>0</TIMEDIFFERENCEDAYS>
  <BUGGYCOMMIT>
    <MESSAGE>#2187 Fix unit test fail</MESSAGE>
    <SHA>18bacff42f8cfca6123551dfbdbbcaf746d2922e</SHA>
  </BUGGYCOMMIT>
  <PATCHCOMMITS>
    <COMMIT>
      <MESSAGE>#2189 Explicitly set content type for the &quot;Page not found&quot; page.</MESSAGE>
      <SHA>c13177b130e4743fc7f32ffd854458b2e01d67fa</SHA>
      <PATCHEDFILES>
        <FILE>src/Presentation/Nop.Web/Controllers/CommonController.cs</FILE>
      </PATCHEDFILES>
    </COMMIT>
  </PATCHCOMMITS>
</ISSUE>
