<?xml version="1.0" ?>
<ISSUE>
  <ISSUENO>276</ISSUENO>
  <ISSUEURL>https://github.com/getredash/redash/issues/276</ISSUEURL>
  <TITLE>multiple data sources do not show in new query page</TITLE>
  <DESCRIPTION>I've add more than one ds with the command &quot;bin/run ./manage.py ds new&quot;, and I can see multiple ds with the command &quot;ds list&quot;, but in the &quot;new query&quot; page, I can see only one data source. I tried to restart redash_web and redash_updater, but that doesn't work.</DESCRIPTION>
  <REPONAME>redash</REPONAME>
  <TIMEDIFFERENCEDAYS>3</TIMEDIFFERENCEDAYS>
  <BUGGYCOMMIT>
    <MESSAGE>Merge pull request #275 from jezdez/fix-search-migration Fix downgrade hash in search vector migration</MESSAGE>
    <SHA>90a576a1d4cfa5ecf085cdb83064f59e74274bfd</SHA>
  </BUGGYCOMMIT>
  <PATCHCOMMITS>
    <COMMIT>
      <MESSAGE>Merge pull request #276 from jezdez/fix-search-migration Fix downgrade hash in search vector migration again</MESSAGE>
      <SHA>520604ebdc0d4c8e2c3e16a012a0b1a22d54eede</SHA>
      <PATCHEDFILES>
        <FILE>migrations/versions/5ec5c84ba61e_.py</FILE>
      </PATCHEDFILES>
    </COMMIT>
  </PATCHCOMMITS>
</ISSUE>
