<?xml version="1.0" ?>
<ISSUE>
  <ISSUENO>18715</ISSUENO>
  <ISSUEURL>https://github.com/TryGhost/Ghost/issues/18715</ISSUEURL>
  <TITLE>Release announcement-bar 1.1.7 version</TITLE>
  <DESCRIPTION>### Issue Summary Getting accessibility issue for announcement bar close button. The issue is already fixed in branch but the version still not released. ### Steps to Reproduce Can be reproduced by lighthouse or pagespeed insights accessibility testing. ### Ghost Version 5.69.0 ### Node.js Version v17 ### How did you install Ghost? Self Hosted on Ubuntu 18.04 ### Database type MySQL 5.7 ### Browser &amp; OS version Chrome 117 on Windows ### Relevant log / error output ```shell Buttons do not have an accessible name ``` ### Code of Conduct - [X] I agree to be friendly and polite to people in this repository</DESCRIPTION>
  <REPONAME>Ghost</REPONAME>
  <TIMEDIFFERENCEDAYS>4</TIMEDIFFERENCEDAYS>
  <BUGGYCOMMIT>
    <MESSAGE>Fixed loading Portal when Stripe is enabled, members disabled and don… (#18757) …ations flag disabled refs https://ghost.slack.com/archives/C02G9E68C/p1698230240376929</MESSAGE>
    <SHA>9cad62d8268a959593176c1dcb5496b3bcbe382a</SHA>
  </BUGGYCOMMIT>
  <PATCHCOMMITS>
    <COMMIT>
      <MESSAGE>Released @tryghost/announcement-bar v1.1.8 fixes https://github.com/TryGhost/Ghost/issues/18715</MESSAGE>
      <SHA>2a9d5a2ea9a0ca1e17b6e54d3803d7bbaf9c348d</SHA>
      <PATCHEDFILES>
        <FILE>apps/announcement-bar/package.json</FILE>
      </PATCHEDFILES>
    </COMMIT>
    <COMMIT>
      <MESSAGE>Released @tryghost/announcement-bar v1.1.8 fixes https://github.com/TryGhost/Ghost/issues/18715</MESSAGE>
      <SHA>14104f8f74ce1bc89db51349e85dce54a7cb2d5e</SHA>
      <PATCHEDFILES>
        <FILE>apps/announcement-bar/package.json</FILE>
      </PATCHEDFILES>
    </COMMIT>
  </PATCHCOMMITS>
</ISSUE>
