<?xml version="1.0" ?>
<ISSUE>
  <ISSUENO>121495</ISSUENO>
  <ISSUEURL>https://github.com/elastic/elasticsearch/issues/121495</ISSUEURL>
  <TITLE>[CI] SetSingleNodeAllocateStepTests testPerformActionSomeShardsOnlyOnNewNodesButNewNodesInvalidAttrs failing</TITLE>
  <DESCRIPTION>**Build Scans:** - [elasticsearch-periodic-platform-support #6135 / oraclelinux-9_platform-support-unix](https://gradle-enterprise.elastic.co/s/kc76r2buewrki) - [elasticsearch-pull-request #54458 / part-2](https://gradle-enterprise.elastic.co/s/sr2u643xaeea6) - [elasticsearch-periodic #6104 / openjdk21_checkpart2_java-fips-matrix](https://gradle-enterprise.elastic.co/s/74sg3ibvdsjls) **Reproduction Line:** ``` ./gradlew &quot;:x-pack:plugin:core:test&quot; --tests &quot;org.elasticsearch.xpack.core.ilm.SetSingleNodeAllocateStepTests.testPerformActionSomeShardsOnlyOnNewNodesButNewNodesInvalidAttrs&quot; -Dtests.seed=6DD3B21F36892442 -Dtests.locale=pt-GW -Dtests.timezone=Asia/Brunei -Druntime.java=23 ``` **Applicable branches:** main **Reproduces locally?:** N/A **Failure History:** [See dashboard](https://es-delivery-stats.elastic.dev/app/dashboards#/view/dcec9e60-72ac-11ee-8f39-55975ded9e63?_g=(refreshInterval:(pause:!t,value:60000),time:(from:now-7d%2Fd,to:now))&amp;_a=(controlGroupState:(initialChildControlState:('0c0c9cb8-ccd2-45c6-9b13-96bac4abc542':(dataViewId:fbbdc689-be23-4b3d-8057-aa402e9ed0c5,fieldName:task.keyword,order:0,selectedOptions:!(),title:'GradleTask',type:optionsListControl),'4e6ad9d6-6fdc-4fcc-bf1a-aa6ca79e0850':(dataViewId:fbbdc689-be23-4b3d-8057-aa402e9ed0c5,fieldName:className.keyword,order:1,selectedOptions:!(org.elasticsearch.xpack.core.ilm.SetSingleNodeAllocateStepTests),title:'Suite',type:optionsListControl),'144933da-5c1b-4257-a969-7f43455a7901':(dataViewId:fbbdc689-be23-4b3d-8057-aa402e9ed0c5,fieldName:name.keyword,order:2,selectedOptions:!(testPerformActionSomeShardsOnlyOnNewNodesButNewNodesInvalidAttrs),title:'Test',type:optionsListControl))))) **Failure Message:** ``` java.lang.AssertionError: unexpected ``` **Issue Reasons:** - [main] 3 failures in test testPerformActionSomeShardsOnlyOnNewNodesButNewNodesInvalidAttrs (1.1% fail rate in 274 executions) **Note:** This issue was created using new test triage automation. Please report issues or feedback to es-delivery.</DESCRIPTION>
  <REPONAME>elasticsearch</REPONAME>
  <TIMEDIFFERENCEDAYS>10</TIMEDIFFERENCEDAYS>
  <BUGGYCOMMIT>
    <MESSAGE>ESQL: Support for _index metadata field in CsvTests (#121261) * ESQL: Support for _index metadata field in CsvTests * Extract INDEX constant to MetadataAttribute * Add comment on capability</MESSAGE>
    <SHA>2838dbb98e8dad7c0af768d7ed5aa89bf0611471</SHA>
  </BUGGYCOMMIT>
  <PATCHCOMMITS>
    <COMMIT>
      <MESSAGE>Mute org.elasticsearch.xpack.core.ilm.SetSingleNodeAllocateStepTests testPerformActionSomeShardsOnlyOnNewNodesButNewNodesInvalidAttrs #121495</MESSAGE>
      <SHA>7eeb908d88fc85717434c5ba724f22e41f2a834f</SHA>
      <PATCHEDFILES>
        <FILE>muted-tests.yml</FILE>
      </PATCHEDFILES>
    </COMMIT>
    <COMMIT>
      <MESSAGE>Unmute `SetSingleNodeAllocateStepTests` This failing test was already fixed by #121266 Fixes #121495</MESSAGE>
      <SHA>73034a25c81aea4dd09ae66c22f0920cdd9b2198</SHA>
      <PATCHEDFILES>
        <FILE>muted-tests.yml</FILE>
      </PATCHEDFILES>
    </COMMIT>
    <COMMIT>
      <MESSAGE>Unmute `SetSingleNodeAllocateStepTests` (#122318) This failing test was already fixed by #121266 Fixes #121495</MESSAGE>
      <SHA>3c18ea6e4454c5977c20eb853e41fb8d80edf8dc</SHA>
      <PATCHEDFILES>
        <FILE>muted-tests.yml</FILE>
      </PATCHEDFILES>
    </COMMIT>
  </PATCHCOMMITS>
</ISSUE>
