<?xml version="1.0" ?>
<ISSUE>
  <ISSUENO>9693</ISSUENO>
  <ISSUEURL>https://github.com/OrchardCMS/OrchardCore/issues/9693</ISSUEURL>
  <TITLE>Trumbowyg icons are giant</TITLE>
  <DESCRIPTION>### Describe the bug Updated to 1.0.0-rc2-16262 and now the trumbowyg icons are giant when using an HTML body part. **EDIT:** Still a problem in 1.0.0-rc2-16296 ### To Reproduce Steps to reproduce the behavior: 1. Create a fresh OC site using the blog theme. 2. Add an HTML body part to the blog post content type. 3. Set the site to use framework CDN. 4. Create a new blog post. ### Screenshots ![image](https://user-images.githubusercontent.com/68876423/122060666-c86b8480-cdbb-11eb-838e-ee770e64759e.png) From the console window: ``` Failed to find a valid digest in the 'integrity' attribute for resource 'https://cdn.jsdelivr.net/npm/trumbowyg@2.24.0/dist/ui/trumbowyg.css' with computed SHA-256 integrity 'c3pFwAU4HTx9A6bnVa7aUSYrnr/bWqPfHEe7UuhE2e8='. The resource has been blocked. ``` ### Workaround Disable CDN from the admin settings</DESCRIPTION>
  <REPONAME>OrchardCore</REPONAME>
  <TIMEDIFFERENCEDAYS>0</TIMEDIFFERENCEDAYS>
  <BUGGYCOMMIT>
    <MESSAGE>GeoPointField Startup (#9688)</MESSAGE>
    <SHA>434da05bbcb4fed985b5a190fd84b26c71a75219</SHA>
  </BUGGYCOMMIT>
  <PATCHCOMMITS>
    <COMMIT>
      <MESSAGE>Trumbowyg CDN Fixes #9693</MESSAGE>
      <SHA>ebd3c3f36bed1552e36421f3e3d1671cff45509a</SHA>
      <PATCHEDFILES>
        <FILE>src/OrchardCore.Modules/OrchardCore.Resources/ResourceManagementOptionsConfiguration.cs</FILE>
      </PATCHEDFILES>
    </COMMIT>
    <COMMIT>
      <MESSAGE>Trumbowyg CDN (#9695) Fixes #9693</MESSAGE>
      <SHA>b9c6b0e4dbfbefc05db35d50f853f185b12b2471</SHA>
      <PATCHEDFILES>
        <FILE>src/OrchardCore.Modules/OrchardCore.Resources/ResourceManagementOptionsConfiguration.cs</FILE>
      </PATCHEDFILES>
    </COMMIT>
  </PATCHCOMMITS>
</ISSUE>
