<?xml version="1.0" ?>
<ISSUE>
  <ISSUENO>5798</ISSUENO>
  <ISSUEURL>https://github.com/nocodb/nocodb/issues/5798</ISSUEURL>
  <TITLE>Bug: eyeSlash icon is not shown in form</TITLE>
  <DESCRIPTION>### Please confirm if bug report does NOT exists already ? - [X] I confirm there is no existing issue for this ### Steps to reproduce ? click on form and look the current behaviour of form ![image](https://github.com/nocodb/nocodb/assets/94478026/11feb2f3-d0f8-43ff-8581-4bf7dd752912) ### Desired Behavior ![image](https://github.com/nocodb/nocodb/assets/94478026/24d4e9f5-2d6d-47f4-b94e-dd173c324a2e) ### Project Details form ### Attachments _No response_</DESCRIPTION>
  <REPONAME>nocodb</REPONAME>
  <TIMEDIFFERENCEDAYS>0</TIMEDIFFERENCEDAYS>
  <BUGGYCOMMIT>
    <MESSAGE>Merge pull request #5786 from nocodb/fix/5753-scroll-issues fix: Grid view scroll related issues</MESSAGE>
    <SHA>7550bdde93fcb290aae4e96c6d325da346e34547</SHA>
  </BUGGYCOMMIT>
  <PATCHCOMMITS>
    <COMMIT>
      <MESSAGE>Merge pull request #5799 from DIWAKARKASHYAP/develop eyeSlash icon is not shown in form #5798</MESSAGE>
      <SHA>be402a45da2c7e5535b6109e9830d3f06ea51aec</SHA>
      <PATCHEDFILES>
        <FILE>packages/nc-gui/components/smartsheet/Form.vue</FILE>
      </PATCHEDFILES>
    </COMMIT>
  </PATCHCOMMITS>
</ISSUE>
