<?xml version="1.0" ?>
<ISSUE>
  <ISSUENO>7748</ISSUENO>
  <ISSUEURL>https://github.com/nocodb/nocodb/issues/7748</ISSUEURL>
  <TITLE>Bug: Unable to add new record to linked table by &quot;add new link&quot;</TITLE>
  <DESCRIPTION>### Please confirm if bug report does NOT exist already ? - [X] I confirm there is no existing issue for this ### Steps to reproduce ? - I'm using app.nocodb.com, haven't validated in a self-hosted installation - Create two new tables within a single base - Add a new field with - Type: &quot;link&quot; - Relation: either &quot;many to many&quot; or &quot;has many&quot; - Child table: whichever table not currently using - On record, select open &quot;linked records&quot; - Select &quot;link records&quot; - select &quot;new record&quot; - Attempt typing into any fields on the new record, **text appears in the previous &quot;link records&quot; window's search bar—not in the &quot;new record&quot; fields.** - I'm able to get data to populate there by right clicking to paste. Typing directly or using keyboard shortcuts is not working for me. ### Desired Behavior Able to type directly into a new linked record's fields without a workaround. ### Project Details NocoDB used in the app.nocodb.com site, not self-installed Bases created within app.nocodb.com, not connected to an external data source ### Attachments https://github.com/nocodb/nocodb/assets/66445285/a6dcccf9-af4f-47ea-b062-0cf9d153895d</DESCRIPTION>
  <REPONAME>nocodb</REPONAME>
  <TIMEDIFFERENCEDAYS>0</TIMEDIFFERENCEDAYS>
  <BUGGYCOMMIT>
    <MESSAGE>Merge pull request #7750 from nocodb/nc-sync/0229 fix: various small issues</MESSAGE>
    <SHA>f2368abe1486e826272c472ed367dc4cc53e23df</SHA>
  </BUGGYCOMMIT>
  <PATCHCOMMITS>
    <COMMIT>
      <MESSAGE>fix(nc-gui): unable to add new record to linked table by `add new link` nocodb/nocodb#7748</MESSAGE>
      <SHA>cc6f3027e9b67b3b970fd9d7db773d7b6ccbad6d</SHA>
      <PATCHEDFILES>
        <FILE>packages/nc-gui/components/virtual-cell/components/ListItems.vue</FILE>
      </PATCHEDFILES>
    </COMMIT>
    <COMMIT>
      <MESSAGE>fix(nc-gui): unable to add new record to linked table by `add new link` nocodb/nocodb#7748</MESSAGE>
      <SHA>653b33d9263f4984cf3276428513b95776336d84</SHA>
      <PATCHEDFILES>
        <FILE>packages/nc-gui/components/virtual-cell/components/ListItems.vue</FILE>
      </PATCHEDFILES>
    </COMMIT>
    <COMMIT>
      <MESSAGE>fix(nc-gui): unable to add new record to linked table by `add new link` nocodb/nocodb#7748</MESSAGE>
      <SHA>3502afe0736eaae9b7f83ebe4e4d924255688dc7</SHA>
      <PATCHEDFILES>
        <FILE>packages/nc-gui/components/virtual-cell/components/ListItems.vue</FILE>
      </PATCHEDFILES>
    </COMMIT>
    <COMMIT>
      <MESSAGE>fix(nc-gui): unable to add new record to linked table by `add new link` nocodb/nocodb#7748</MESSAGE>
      <SHA>52eb8039b29dce7f5434ba963d926e10ca68b168</SHA>
      <PATCHEDFILES>
        <FILE>packages/nc-gui/components/virtual-cell/components/ListItems.vue</FILE>
      </PATCHEDFILES>
    </COMMIT>
  </PATCHCOMMITS>
</ISSUE>
