<?xml version="1.0" ?>
<ISSUE>
  <ISSUENO>2517</ISSUENO>
  <ISSUEURL>https://github.com/apache/apisix/issues/2517</ISSUEURL>
  <TITLE>Use APISIX_WORKER_PROCESSES instead of APIX_WORKER_PROCESSES?</TITLE>
  <DESCRIPTION>The former one is more compatible with the name of this project. CC @ShiningRush @membphis</DESCRIPTION>
  <REPONAME>apisix</REPONAME>
  <TIMEDIFFERENCEDAYS>3</TIMEDIFFERENCEDAYS>
  <BUGGYCOMMIT>
    <MESSAGE>CI: move etcd cluster in docker (#2225)</MESSAGE>
    <SHA>1dfc4cdacd620e6d59c3d4c75506ff80581612eb</SHA>
  </BUGGYCOMMIT>
  <PATCHCOMMITS>
    <COMMIT>
      <MESSAGE>change: rename APIX_WORKER_PROCESSES to APISIX_WORKER_PROCESSES Close #2517.</MESSAGE>
      <SHA>3c4c3cffe7bc40a9fa2c643b57356348e352f5d6</SHA>
      <PATCHEDFILES>
        <FILE>.travis/apisix_cli_test.sh</FILE>
        <FILE>bin/apisix</FILE>
        <FILE>conf/config-default.yaml</FILE>
      </PATCHEDFILES>
    </COMMIT>
    <COMMIT>
      <MESSAGE>change: rename APIX_WORKER_PROCESSES to APISIX_WORKER_PROCESSES (#2552) Close #2517.</MESSAGE>
      <SHA>b6eb6f48422ed3feeab6de76ad7cb5978af99eda</SHA>
      <PATCHEDFILES>
        <FILE>.travis/apisix_cli_test.sh</FILE>
        <FILE>bin/apisix</FILE>
        <FILE>conf/config-default.yaml</FILE>
      </PATCHEDFILES>
    </COMMIT>
  </PATCHCOMMITS>
</ISSUE>
