<?xml version="1.0" ?>
<ISSUE>
  <ISSUENO>1012</ISSUENO>
  <ISSUEURL>https://github.com/harness/harness/issues/1012</ISSUEURL>
  <TITLE>github URL format</TITLE>
  <DESCRIPTION>Not sure why, but one of my added repos is trying to use git://github.com/meanpath/json2csv where it should be using git@github.com:meanpath/json2csv. All my other repos use it without issue. I tried running &quot;drone delete github.com/meanpath/json2csv&quot; so i could delete and re-add, but it tells me &quot;Unauthorized&quot;. Any ideas?</DESCRIPTION>
  <REPONAME>harness</REPONAME>
  <TIMEDIFFERENCEDAYS>0</TIMEDIFFERENCEDAYS>
  <BUGGYCOMMIT>
    <MESSAGE>[CLI] move swagger+server under cli/operations (#1011)</MESSAGE>
    <SHA>c270b8f7b9c2bc76d2938b790c70aab77538f20c</SHA>
  </BUGGYCOMMIT>
  <PATCHCOMMITS>
    <COMMIT>
      <MESSAGE>Fix line wrapping in PR when file name is long (#1012)</MESSAGE>
      <SHA>92be6ec51b0e7dd22eeb294f6e592cc5ebbc9f99</SHA>
      <PATCHEDFILES>
        <FILE>web/src/components/DiffViewer/DiffViewer.module.scss</FILE>
        <FILE>web/src/components/DiffViewer/DiffViewer.module.scss.d.ts</FILE>
        <FILE>web/src/components/DiffViewer/DiffViewer.tsx</FILE>
        <FILE>web/src/pages/PullRequest/Conversation/CodeCommentHeader.tsx</FILE>
        <FILE>web/src/pages/PullRequest/Conversation/Conversation.module.scss</FILE>
        <FILE>web/src/pages/PullRequest/Conversation/Conversation.module.scss.d.ts</FILE>
        <FILE>web/src/pages/Repository/RepositoryContent/ContentHeader/ContentHeader.tsx</FILE>
        <FILE>web/src/pages/Repository/RepositoryContent/FileContent/GitBlame.tsx</FILE>
      </PATCHEDFILES>
    </COMMIT>
  </PATCHCOMMITS>
</ISSUE>
