<?xml version="1.0" ?>
<ISSUE>
  <ISSUENO>9830</ISSUENO>
  <ISSUEURL>https://github.com/ansible/awx/issues/9830</ISSUEURL>
  <TITLE>Branding issue: AWX 18 in K3s uses the awx icons and logos everywhere except &quot;info-&gt;about&quot;</TITLE>
  <DESCRIPTION>&lt;!-- Issues are for **concrete, actionable bugs and feature requests** only - if you're just asking for debugging help or technical support, please use: - http://webchat.freenode.net/?channels=ansible-awx - https://groups.google.com/forum/#!forum/awx-project We have to limit this because of limited volunteer time to respond to issues! --&gt; ##### ISSUE TYPE - Bug Report (branding) ##### SUMMARY When I look at &quot;Info-&gt;About&quot; I see the &quot;angry potato&quot; logo instead of the AWX logo ##### ENVIRONMENT * AWX version: 18.0.0 * AWX install method: K3s using awx-operator * Ansible version: unknown (see #9829) * Operating System: K3s on debian buster * Web Browser: Firefox 87 ##### STEPS TO REPRODUCE Deploy AWX 18.0.0 on K3s using the awx operator, then after logging in open &quot;info-&gt;About&quot; ##### EXPECTED RESULTS I expect the AWX logo since it's used everywhere else ##### ACTUAL RESULTS I see the development version logo (the &quot;angry potato&quot;) ##### ADDITIONAL INFORMATION</DESCRIPTION>
  <REPONAME>awx</REPONAME>
  <TIMEDIFFERENCEDAYS>6</TIMEDIFFERENCEDAYS>
  <BUGGYCOMMIT>
    <MESSAGE>Merge pull request #9843 from tiagodread/fix-doc-link Remove duple // for docs link on PageHeaderToolBar Related: #9842 Reviewed-by: Jake McDermott &lt;yo@jakemcdermott.me&gt;</MESSAGE>
    <SHA>e8f0a3dbd5b4e331bccf584dbcf99f148f0f3bd8</SHA>
  </BUGGYCOMMIT>
  <PATCHCOMMITS>
    <COMMIT>
      <MESSAGE>Merge pull request #9836 from jakemcdermott/fix-9830-9296 Use shared logo img and dynamic copyright date for #9830, #9296 Reviewed-by: Kersom &lt;None&gt;</MESSAGE>
      <SHA>840f5b72645c5f8a60b5cc1552f616fe0d41805f</SHA>
      <PATCHEDFILES>
        <FILE>awx/ui_next/.eslintrc</FILE>
        <FILE>awx/ui_next/src/components/About/About.jsx</FILE>
        <FILE>awx/ui_next/src/components/About/brand-logo.svg</FILE>
      </PATCHEDFILES>
    </COMMIT>
  </PATCHCOMMITS>
</ISSUE>
