<?xml version="1.0" ?>
<ISSUE>
  <ISSUENO>5067</ISSUENO>
  <ISSUEURL>https://github.com/ansible/awx/issues/5067</ISSUEURL>
  <TITLE>Add edit button to Template list rows</TITLE>
  <DESCRIPTION>##### ISSUE TYPE - Feature Idea ##### SUMMARY Edit button should appear on each row that the logged in user can edit (summary_fields.user_capabilities.edit)</DESCRIPTION>
  <REPONAME>awx</REPONAME>
  <TIMEDIFFERENCEDAYS>7</TIMEDIFFERENCEDAYS>
  <BUGGYCOMMIT>
    <MESSAGE>Merge pull request #5068 from ansible/add-yamllint Add yamllint to dev dependencies</MESSAGE>
    <SHA>e4e28576052a9627496a34907eab4c32eeafb3a8</SHA>
  </BUGGYCOMMIT>
  <PATCHCOMMITS>
    <COMMIT>
      <MESSAGE>Merge pull request #5067 from jbradberry/danger-danger-will-robinson-4.0 Remove isolated instances and groups</MESSAGE>
      <SHA>f4fa0ccc9fcb781ca7992a53e00e911a855cf8cb</SHA>
      <PATCHEDFILES>
        <FILE>awx/main/migrations/0139_isolated_removal.py</FILE>
      </PATCHEDFILES>
    </COMMIT>
  </PATCHCOMMITS>
</ISSUE>
