<?xml version="1.0" ?>
<ISSUE>
  <ISSUENO>268</ISSUENO>
  <ISSUEURL>https://github.com/nightscout/cgm-remote-monitor/issues/268</ISSUEURL>
  <TITLE>Calculate current % unit test coverage</TITLE>
  <DESCRIPTION/>
  <REPONAME>cgm-remote-monitor</REPONAME>
  <TIMEDIFFERENCEDAYS>67</TIMEDIFFERENCEDAYS>
  <BUGGYCOMMIT>
    <MESSAGE>Merge pull request #363 from dduugg/feature/badges unify README badge styles</MESSAGE>
    <SHA>0a7652add6b48895c9c3a50c32d84ae9219fcca1</SHA>
  </BUGGYCOMMIT>
  <PATCHCOMMITS>
    <COMMIT>
      <MESSAGE>add coverage report to travis script resolves #268</MESSAGE>
      <SHA>034bcefc0f477d48b51538be2ff8b661b548a5d3</SHA>
      <PATCHEDFILES>
        <FILE>.gitignore</FILE>
        <FILE>.travis.yml</FILE>
        <FILE>Makefile</FILE>
        <FILE>README.md</FILE>
        <FILE>package.json</FILE>
      </PATCHEDFILES>
    </COMMIT>
  </PATCHCOMMITS>
</ISSUE>
