<?xml version="1.0" ?>
<ISSUE>
  <ISSUENO>23022</ISSUENO>
  <ISSUEURL>https://github.com/Dolibarr/dolibarr/issues/23022</ISSUEURL>
  <TITLE>Translation inconsistent</TITLE>
  <DESCRIPTION>### Bug Translations in the companies are inconsistent. I'm using de_DE as language. If navigating to /societe/card.php, you can (with module `notifications` enabled) see a tab 'Benachrichtigungen'. But while accessing `societe/consumption.php` or `societe/paymentmodes.php`, it uses the default fallback 'Notifications'. I followed the paths in the code to `core/class/translate.class.php` (line 612, function `trans($key....)`. The associative array `tab_translate` in the `translate.class.php` is different for the three frontend pages (`card.php`, `consumption.php` and `paymentmodes.php`). For `card.php`, the key 'Notifications' is set. But the key isn't present in the both other cases. As I first would have to read into the docs and the translation mechanism, I assume it would be much quicker if you just check it yourself. P.S.: In the `langs/de_DE/companies.lang` file is no 'Notifications' key set either. ### Environment Version 16.0.2 ### Environment OS AlmaLinux release 8.6 ### Environment Web server Apache/2.4.37 ### Environment PHP PHP 7.4.33 ### Environment Database 10.6.10-MariaDB ### Environment URL(s) _No response_ ### Expected and actual behavior _No response_ ### Steps to reproduce the behavior _No response_ ### Attached files ![image](https://user-images.githubusercontent.com/18233867/204256836-76c95634-c923-41fb-9582-c34cb1516457.png) ![image](https://user-images.githubusercontent.com/18233867/204256972-875ab6c9-1d2b-41b6-8186-3345591c05c7.png) ![image](https://user-images.githubusercontent.com/18233867/204256909-9fdda1ef-dff6-4f8b-8601-727e7c7372ec.png)</DESCRIPTION>
  <REPONAME>dolibarr</REPONAME>
  <TIMEDIFFERENCEDAYS>698</TIMEDIFFERENCEDAYS>
  <BUGGYCOMMIT>
    <MESSAGE>Fix: Skip UtilsTest on windows where ls is not available (#28601) # Fix: Skip UtilsTest on windows where ls is not available The test in question uses 'ls' which is not available on windows. This change limits the execution to non windows systems.</MESSAGE>
    <SHA>faf00c35e36e82fa48c0170821138772a42cb99d</SHA>
  </BUGGYCOMMIT>
  <PATCHCOMMITS>
    <COMMIT>
      <MESSAGE>FIX issue #23022 (#28590) * FIX issue #23022 * no longer necessary * no longer necessary * no longer necessary * no longer necessary * no longer necessary * no longer necessary * no longer necessary</MESSAGE>
      <SHA>9e1cfb7c52f8c2ec67562b60fbfc359a20eb069a</SHA>
      <PATCHEDFILES>
        <FILE>htdocs/core/lib/company.lib.php</FILE>
        <FILE>htdocs/partnership/partnership_list.php</FILE>
        <FILE>htdocs/societe/agenda.php</FILE>
        <FILE>htdocs/societe/document.php</FILE>
        <FILE>htdocs/societe/messaging.php</FILE>
        <FILE>htdocs/societe/note.php</FILE>
        <FILE>htdocs/societe/price.php</FILE>
        <FILE>htdocs/societe/project.php</FILE>
      </PATCHEDFILES>
    </COMMIT>
  </PATCHCOMMITS>
</ISSUE>
