<?xml version="1.0" ?>
<ISSUE>
  <ISSUENO>1584</ISSUENO>
  <ISSUEURL>https://github.com/nopSolutions/nopCommerce/issues/1584</ISSUEURL>
  <TITLE>Hide the choice of payment method on checkout if &quot;Use my reward points&quot; is selected and points are enough to pay the order in full</TITLE>
  <DESCRIPTION>In this case payment method selection is not required. Hide it dynamically. Do it on the step Payment method (for both the multistep and the one-page checkout)</DESCRIPTION>
  <REPONAME>nopCommerce</REPONAME>
  <TIMEDIFFERENCEDAYS>88</TIMEDIFFERENCEDAYS>
  <BUGGYCOMMIT>
    <MESSAGE>Source code typo fixed</MESSAGE>
    <SHA>f274d37f4b5f80af04063f062a572ebb6d953c68</SHA>
  </BUGGYCOMMIT>
  <PATCHCOMMITS>
    <COMMIT>
      <MESSAGE>#1584 There's no need to display payment methods during checkout if &quot;Use my reward points&quot; is selected and earned points are enough to pay the order in full</MESSAGE>
      <SHA>6fcc9d754748400909fc203273eb4a29ad5559fe</SHA>
      <PATCHEDFILES>
        <FILE>src/Libraries/Nop.Services/Orders/IOrderTotalCalculationService.cs</FILE>
        <FILE>src/Libraries/Nop.Services/Orders/OrderTotalCalculationService.cs</FILE>
        <FILE>src/Presentation/Nop.Web/Controllers/CheckoutController.cs</FILE>
        <FILE>src/Presentation/Nop.Web/Models/Checkout/CheckoutPaymentMethodModel.cs</FILE>
        <FILE>src/Presentation/Nop.Web/Scripts/public.onepagecheckout.js</FILE>
        <FILE>src/Presentation/Nop.Web/Views/Checkout/OpcPaymentMethods.cshtml</FILE>
        <FILE>src/Presentation/Nop.Web/Views/Checkout/PaymentMethod.cshtml</FILE>
      </PATCHEDFILES>
    </COMMIT>
  </PATCHCOMMITS>
</ISSUE>
