<?xml version="1.0" ?>
<ISSUE>
  <ISSUENO>5208</ISSUENO>
  <ISSUEURL>https://github.com/nopSolutions/nopCommerce/issues/5208</ISSUEURL>
  <TITLE>Discounts. Add &quot;basic&quot; and &quot;advanced&quot; modes</TITLE>
  <DESCRIPTION>The following fields will be displayed for the &quot;Advanced&quot; mode only: - Maximum discount amount - Start date - End date - Cumulative with other discounts - Discount limitation - Admin comment - &quot;Requirements&quot; block</DESCRIPTION>
  <REPONAME>nopCommerce</REPONAME>
  <TIMEDIFFERENCEDAYS>330</TIMEDIFFERENCEDAYS>
  <BUGGYCOMMIT>
    <MESSAGE>#5674 Changed decimal precision for entries to 4</MESSAGE>
    <SHA>28e52a0e493d5c22a12282e402e7d36d2728f648</SHA>
  </BUGGYCOMMIT>
  <PATCHCOMMITS>
    <COMMIT>
      <MESSAGE>#5208 Discounts. Add basic and advanced modes (#5929)</MESSAGE>
      <SHA>2970bcde489ab268167ad5d17242afcf3ee29f12</SHA>
      <PATCHEDFILES>
        <FILE>src/Presentation/Nop.Web/Areas/Admin/Views/Discount/_CreateOrUpdate.Info.cshtml</FILE>
        <FILE>src/Presentation/Nop.Web/Areas/Admin/Views/Discount/_CreateOrUpdate.cshtml</FILE>
      </PATCHEDFILES>
    </COMMIT>
  </PATCHCOMMITS>
</ISSUE>
