<?xml version="1.0" ?>
<ISSUE>
  <ISSUENO>4741</ISSUENO>
  <ISSUEURL>https://github.com/nopSolutions/nopCommerce/issues/4741</ISSUEURL>
  <TITLE>Replace old favicon in popup windows (admin panel)</TITLE>
  <DESCRIPTION>nopCommerce version: 4.30 rc ![ab0d33e570](https://user-images.githubusercontent.com/16681184/81703852-c9720a00-9475-11ea-993b-cd7412b0776e.jpg)</DESCRIPTION>
  <REPONAME>nopCommerce</REPONAME>
  <TIMEDIFFERENCEDAYS>1</TIMEDIFFERENCEDAYS>
  <BUGGYCOMMIT>
    <MESSAGE>#4717 some refactoring</MESSAGE>
    <SHA>0ab5569655544039081fdb44e13dff83178dbf00</SHA>
  </BUGGYCOMMIT>
  <PATCHCOMMITS>
    <COMMIT>
      <MESSAGE>#4741 changed favicon</MESSAGE>
      <SHA>200cdbe6ccbe245aaab9bd31d1318c3763b9dcc6</SHA>
      <PATCHEDFILES>
        <FILE>src/Presentation/Nop.Web/wwwroot/favicon.ico</FILE>
      </PATCHEDFILES>
    </COMMIT>
  </PATCHCOMMITS>
</ISSUE>
