<?xml version="1.0" ?>
<ISSUE>
  <ISSUENO>6718</ISSUENO>
  <ISSUEURL>https://github.com/ansible/awx/issues/6718</ISSUEURL>
  <TITLE>Add &quot;of&quot; to &quot;Run on&quot; field in schedule form</TITLE>
  <DESCRIPTION>##### ISSUE TYPE - Feature Idea ##### SUMMARY ![Screenshot_20200415_101505](https://user-images.githubusercontent.com/9889020/79348253-c6314000-7f02-11ea-90f6-e74610f3fb8f.png) This could be more readable by adding &quot;of&quot; to the &quot;The&quot; option so that it read like: `The First ___ day of [month]`</DESCRIPTION>
  <REPONAME>awx</REPONAME>
  <TIMEDIFFERENCEDAYS>43</TIMEDIFFERENCEDAYS>
  <BUGGYCOMMIT>
    <MESSAGE>Merge pull request #7147 from beeankha/pagerduty_approval_notification_fix Fix Approval Notifications for PagerDuty Reviewed-by: https://github.com/apps/softwarefactory-project-zuul</MESSAGE>
    <SHA>09caf729f1385492c3d9159009a7187bbe3d161d</SHA>
  </BUGGYCOMMIT>
  <PATCHCOMMITS>
    <COMMIT>
      <MESSAGE>Add &quot;of&quot; to &quot;Run on&quot; field in schedule form Also, add a few strings to internationalization. closes: https://github.com/ansible/awx/issues/6718</MESSAGE>
      <SHA>1c8fb0636c1192da38a2f7ed90683d9f611f7be8</SHA>
      <PATCHEDFILES>
        <FILE>awx/ui_next/src/components/Schedule/shared/FrequencyDetailSubform.jsx</FILE>
      </PATCHEDFILES>
    </COMMIT>
  </PATCHCOMMITS>
</ISSUE>
