<?xml version="1.0" ?>
<ISSUE>
  <ISSUENO>20271</ISSUENO>
  <ISSUEURL>https://github.com/strapi/strapi/issues/20271</ISSUEURL>
  <TITLE>Filter by text field with &quot;&amp;&quot; symbol doesn't work</TITLE>
  <DESCRIPTION>## Bug report ### Required System information - Node.js version: 18.20.2 - Yarn version: 1.22.22 - Strapi version: v4.24.1 - Database: postgres - Operating system: darwin-arm64 - Is your project Javascript or Typescript: Javascript ### Describe the bug Filter by text field with &quot;&amp;&quot; symbol doesn't work. Search string is cut up to &amp; symbol and no results with &quot;is&quot; operand ### Steps to reproduce the behavior 1. Create any entity at collection type that text field contains ampersand (&amp;) symbol. Eg, create article with title &quot;Test article &amp; issue reproduce&quot; ![image](https://github.com/strapi/strapi/assets/46565276/45583861-aee0-4676-a799-e95fd37bd7c9) 2. Go to list of collection type and using &quot;Filters&quot; button select text field, &quot;is&quot; operand and text with &amp; symbol ![image](https://github.com/strapi/strapi/assets/46565276/9f4de5c7-ebe8-4cc0-a419-741dec696377) 3. Click &quot;Add filter&quot; 4. Check what filter is applied ![image](https://github.com/strapi/strapi/assets/46565276/8358f163-5c7b-4177-ad09-520b90d967cb) ### Expected behavior Filter should be applied correctly and display found record, like if there are no &amp; symbol in search: ![image](https://github.com/strapi/strapi/assets/46565276/415c28ca-fb0a-447e-940f-7aa27f65afed) ### Additional context Some details from network tab: Request URL: `http://127.0.0.1:1337/content-manager/collection-types/api::article.article?page=1&amp;pageSize=10&amp;sort=title:ASC&amp;filters[$and][0][title][$eq]=Test%20article%20&amp;%20issue%20reproduce=` Query parameters that applied: ``` page: 1 pageSize: 10 sort: title:ASC filters[$and][0][title][$eq]: Test article issue reproduce: ``` ![image](https://github.com/strapi/strapi/assets/46565276/fa98341b-2dcd-4b3f-9883-54c8c2e48e86)</DESCRIPTION>
  <REPONAME>strapi</REPONAME>
  <TIMEDIFFERENCEDAYS>142</TIMEDIFFERENCEDAYS>
  <BUGGYCOMMIT>
    <MESSAGE>chore: workflow for v4 branch (#21466)</MESSAGE>
    <SHA>28b4e58b04df82c9b81898ea15f84c46fb85e8ab</SHA>
  </BUGGYCOMMIT>
  <PATCHCOMMITS>
    <COMMIT>
      <MESSAGE>fix: Filter by text field with &quot;&amp;&quot; symbol doesn't work #20271 (#21406) * fix: handle special characters in text field filtering * fix: handle special characters in text field filtering * fix: handle special characters in text field filtering * fix: handle special characters in text field filtering * fix: handle special characters in text field filtering</MESSAGE>
      <SHA>69ef78b47194ae2f71697f774760811c9926fc76</SHA>
      <PATCHEDFILES>
        <FILE>packages/core/admin/admin/src/components/Filters.tsx</FILE>
        <FILE>packages/core/content-manager/admin/src/pages/ListView/ListViewPage.tsx</FILE>
        <FILE>packages/core/content-manager/admin/src/services/documents.ts</FILE>
        <FILE>packages/core/upload/admin/src/components/FilterList/index.jsx</FILE>
        <FILE>packages/core/upload/admin/src/components/FilterList/tests/__snapshots__/index.test.js.snap</FILE>
        <FILE>packages/core/upload/admin/src/components/FilterPopover/index.jsx</FILE>
      </PATCHEDFILES>
    </COMMIT>
  </PATCHCOMMITS>
</ISSUE>
