<?xml version="1.0" ?>
<ISSUE>
  <ISSUENO>31396</ISSUENO>
  <ISSUEURL>https://github.com/mastodon/mastodon/issues/31396</ISSUEURL>
  <TITLE>Authorize Interaction padding bug on mobile</TITLE>
  <DESCRIPTION>### Steps to reproduce the problem 1. Open a browser on a iOS device 2. Navigate to a mastodon server 3. Click on the &quot;Follow&quot; button or favourite/boost button while not logged in 4. See the modal with no padding ### Expected behaviour There should be padding ### Actual behaviour There was no padding ### Detailed description _No response_ ### Mastodon instance mastodon.social ### Mastodon version v4.3.0-nightly.2024-08-12 ### Browser name and version Chrome 127.0.6533.100 ### Operating system macOS 14.4.1 ### Technical details ![IMG_6349](https://github.com/user-attachments/assets/ae0107c2-8468-4d22-997f-cd899bbdffc7)</DESCRIPTION>
  <REPONAME>mastodon</REPONAME>
  <TIMEDIFFERENCEDAYS>0</TIMEDIFFERENCEDAYS>
  <BUGGYCOMMIT>
    <MESSAGE>Add missing Appeals link under Moderation in navigiation (#31071)</MESSAGE>
    <SHA>b42661ba95b7872ba278fca9b0fee8faffd89e52</SHA>
  </BUGGYCOMMIT>
  <PATCHCOMMITS>
    <COMMIT>
      <MESSAGE>Fix modal border and padding inconsistencies Fixes #31396</MESSAGE>
      <SHA>7e4fc6c278c8669fab160aebee069bbd873c10f9</SHA>
      <PATCHEDFILES>
        <FILE>app/javascript/styles/mastodon/components.scss</FILE>
        <FILE>app/javascript/styles/mastodon/variables.scss</FILE>
      </PATCHEDFILES>
    </COMMIT>
  </PATCHCOMMITS>
</ISSUE>
